{
	"spell": [
		{
			"name": "Fuetada d'ego",
			"source": "UAFighterRogueWizard",
			"page": 7,
			"level": 4,
			"school": "E",
			"time": [
				{
					"number": 1,
					"unit": "action"
				}
			],
			"range": {
				"type": "point",
				"distance": {
					"type": "feet",
					"amount": 30
				}
			},
			"components": {
				"v": true
			},
			"duration": [
				{
					"type": "timed",
					"duration": {
						"type": "minute",
						"amount": 1
					},
					"concentration": true
				}
			],
			"entries": [
				"Fueteges la ment d'una criatura que puguis veure dins del rang, omplint-la de desesperació. L'objectiu ha de realitzar una tirada de salvació d'Intel·ligència. Si la falla, té desavantatge en les tirades d'atac, les proves de capacitat i les tirades de salvació, i no pot llençar conjurs. Al final de cadascun dels seus torns, l'objectiu pot tornar a realitzar una tirada de salvació d'Intel·ligència. Si la supera, el conjur acaba per a ell."
			],
			"savingThrow": [
				"intelligence"
			],
			"miscTags": [
				"SGT"
			],
			"areaTags": [
				"ST"
			]
		},
		{
			"name": "Insinuació d'identitat",
			"source": "UAFighterRogueWizard",
			"page": 7,
			"level": 1,
			"school": "E",
			"time": [
				{
					"number": 1,
					"unit": "action"
				}
			],
			"range": {
				"type": "point",
				"distance": {
					"type": "feet",
					"amount": 60
				}
			},
			"components": {
				"v": true,
				"s": true
			},
			"duration": [
				{
					"type": "timed",
					"duration": {
						"type": "minute",
						"amount": 1
					},
					"concentration": true
				}
			],
			"entries": [
				"Desencadenes un torrent de desitjos conflictius dins la ment d'una criatura que puguis veure dins del rang, perjudicant la seva capacitat de prendre decisions. L'objectiu ha de realitzar una tirada de salvació de Saviesa. Si la falla, queda incapacitat. Al final de cadascun dels seus torns, rep {@damage 1d12} de dany psíquic i pot tornar a realitzar una tirada de salvació de Saviesa. Si la supera, el conjur acaba per a ell."
			],
			"damageInflict": [
				"psychic"
			],
			"conditionInflict": [
				"incapacitated"
			],
			"savingThrow": [
				"wisdom"
			],
			"miscTags": [
				"SGT"
			],
			"areaTags": [
				"ST"
			]
		},
		{
			"name": "Fortalesa de l'intel·lecte",
			"source": "UAFighterRogueWizard",
			"page": 7,
			"level": 5,
			"school": "A",
			"time": [
				{
					"number": 1,
					"unit": "action"
				}
			],
			"range": {
				"type": "point",
				"distance": {
					"type": "self"
				}
			},
			"components": {
				"v": true,
				"s": true
			},
			"duration": [
				{
					"type": "timed",
					"duration": {
						"type": "minute",
						"amount": 10
					},
					"concentration": true
				}
			],
			"entries": [
				"Crees una barrera lleugerament brillant de poder psíquic protector al teu voltant. Fins que el conjur acabi, tens avantatge en les tirades de salvació.",
				"Quan una altra criatura que puguis veure fins a 30 peus de tu falla una tirada de salvació, pots fer servir la teva reacció per fer que torni a realitzar la tirada. El resultat vàlid serà el d'aquesta nova tirada."
			],
			"miscTags": [
				"SGT"
			]
		},
		{
			"name": "Barrera mental",
			"source": "UAFighterRogueWizard",
			"page": 7,
			"level": 2,
			"school": "A",
			"time": [
				{
					"number": 1,
					"unit": "reaction",
					"condition": ", que duus a terme quan ets obligat a realitzar una tirada de salvació d'Intel·ligència, de Saviesa o de Carisma"
				}
			],
			"range": {
				"type": "point",
				"distance": {
					"type": "self"
				}
			},
			"components": {
				"v": true
			},
			"duration": [
				{
					"type": "timed",
					"duration": {
						"type": "round",
						"amount": 1
					}
				}
			],
			"entries": [
				"Et protegeixes la ment amb una paret de pensaments constants i repetitius. Fins al començament del teu pròxim torn, tens avantatge en les tirades de salvació d'Intel·ligència, de Saviesa i de Carisma, i tens resistència al dany psíquic."
			]
		},
		{
			"name": "Estella mental",
			"source": "UAFighterRogueWizard",
			"page": 7,
			"level": 0,
			"school": "E",
			"time": [
				{
					"number": 1,
					"unit": "action"
				}
			],
			"range": {
				"type": "point",
				"distance": {
					"type": "feet",
					"amount": 60
				}
			},
			"components": {
				"v": true
			},
			"duration": [
				{
					"type": "timed",
					"duration": {
						"type": "round",
						"amount": 1
					}
				}
			],
			"entries": [
				"Introdueixes una estella desorientadora d'energia psíquica dins la ment d'una criatura que puguis veure dins del rang. La criatura ha de realitzar una tirada de salvació d'Intel·ligència. Si la falla, rep {@damage 1d6} de dany psíquic i resta {@dice 1d4} a la següent tirada de salvació que realitzi abans del teu pròxim torn."
			],
			"entriesHigherLevel": [
				{
					"type": "entries",
					"name": "En nivells superiors",
					"entries": [
						"El dany del conjur augmenta {@dice 1d6} en arribar a nivell 5 ({@damage 2d6}), a nivell 11 ({@damage 3d6}), i a nivell 17({@damage 4d6})."					]
				}
			],
			"scalingLevelDice": {
				"label": "psychic damage",
				"scaling": {
					"1": "1d6",
					"5": "2d6",
					"11": "3d6",
					"17": "4d6"
				}
			},
			"damageInflict": [
				"psychic"
			],
			"savingThrow": [
				"intelligence"
			],
			"miscTags": [
				"SCL",
				"SGT"
			],
			"areaTags": [
				"ST"
			]
		},
		{
			"name": "Estocada mental",
			"source": "UAFighterRogueWizard",
			"page": 7,
			"level": 2,
			"school": "E",
			"time": [
				{
					"number": 1,
					"unit": "bonus"
				}
			],
			"range": {
				"type": "point",
				"distance": {
					"type": "feet",
					"amount": 60
				}
			},
			"components": {
				"v": true,
				"s": true
			},
			"duration": [
				{
					"type": "timed",
					"duration": {
						"type": "round",
						"amount": 1
					}
				}
			],
			"entries": [
				"Llences una llança de disrupció psíquica a la ment d'una criatura que puguis veure dins del rang. L'objectiu ha de realitzar una tirada de salvació d'Intel·ligència. Si la falla, rep {@damage 3d6} de dany psíquic, i no pot realitzar cap reacció fins al final del seu pròxim torn. A més a més, en el seu pròxim torn, ha d'escollir si realitzar una acció, un moviment o una acció addicional (només una de les tres). Si supera la tirada de salvació, rep la meitat del dany, però no pateix cap altre efecte."
			],
			"entriesHigherLevel": [
				{
					"type": "entries",
					"name": "En nivells superiors",
					"entries": [
						"Quan llences aquest conjur fent servir un espai de conjur de nivell 3 o superior, pots escollir com a objectiu una criatura addicional per cada nivell per sobre de 2. La criatura ha d'estar fins a 30 peus d'un altre objectiu."
					]
				}
			],
			"damageInflict": [
				"psychic"
			],
			"savingThrow": [
				"intelligence"
			],
			"miscTags": [
				"SGT"
			],
			"areaTags": [
				"ST",
				"MT"
			]
		},
		{
			"name": "Explosió psiònica",
			"source": "UAFighterRogueWizard",
			"page": 8,
			"level": 3,
			"school": "V",
			"time": [
				{
					"number": 1,
					"unit": "action"
				}
			],
			"range": {
				"type": "cone",
				"distance": {
					"type": "feet",
					"amount": 30
				}
			},
			"components": {
				"v": true
			},
			"duration": [
				{
					"type": "instant"
				}
			],
			"entries": [
				"Desencadenes una onada destructora de poder mental en un con de 30 peus. Cada criatura dins de l'àrea ha de realitzar una tirada de salvació de Destresa. Si la falla, rep {@damage 5d8} de dany per força, és empesa 20 peus per allunyar-se de tu i queda {@condition prone}. Si la supera, rep la meitat del dany, però no pateix cap altre efecte."
			],
			"entriesHigherLevel": [
				{
					"name": "En nivells superiors",
					"type": "entries",
					"entries": [
						"Quan llences aquest conjur fent servir un espai de conjur de nivell 4 o superior, el dany augmenta {@scaledamage 5d8|3-9|1d8} per cada nivell per sobre de 3."
					]
				}
			],
			"damageInflict": [
				"force"
			],
			"conditionInflict": [
				"prone"
			],
			"savingThrow": [
				"dexterity"
			],
			"miscTags": [
				"FMV"
			],
			"areaTags": [
				"N"
			]
		},
		{
			"name": "Xoc psíquic",
			"source": "UAFighterRogueWizard",
			"page": 8,
			"level": 6,
			"school": "E",
			"time": [
				{
					"number": 1,
					"unit": "action"
				}
			],
			"range": {
				"type": "point",
				"distance": {
					"type": "feet",
					"amount": 60
				}
			},
			"components": {
				"v": true,
				"s": true
			},
			"duration": [
				{
					"type": "timed",
					"duration": {
						"type": "minute",
						"amount": 1
					}
				}
			],
			"entries": [
				"Sobrecarregues la ment d'una criatura que puguis veure dins del rang, omplint-ne la psique d'emocions discordants. L'objectiu ha de realitzar una tirada de salvació d'Intel·ligència. SI la falla, rep {@damage 12d6} de dany psíquic i queda {@condition stunned} durant 1 minut. Si la supera, rel la meitat del dany, però no pateix cap altre efecte.",
				"La criatura {@condition stunned} pot realitzar una tirada de salvació d'Intel·ligència al final de cadascun dels seus torns. Si la supera, el conjur acaba per a ella."
			],
			"damageInflict": [
				"psychic"
			],
			"conditionInflict": [
				"stunned"
			],
			"savingThrow": [
				"intelligence"
			],
			"miscTags": [
				"SGT"
			],
			"areaTags": [
				"ST"
			]
		},
		{
			"name": "Escut de pensaments",
			"source": "UAFighterRogueWizard",
			"page": 8,
			"level": 2,
			"school": "A",
			"time": [
				{
					"number": 1,
					"unit": "action"
				}
			],
			"range": {
				"type": "point",
				"distance": {
					"type": "touch"
				}
			},
			"components": {
				"v": true,
				"s": true
			},
			"duration": [
				{
					"type": "timed",
					"duration": {
						"type": "hour",
						"amount": 8
					}
				}
			],
			"entries": [
				"Teixeixes un vel ennuvolat sobre la ment d'una criatura que toquis. Fins que el conjur acabi, la ment de l'objectiu no pot ser llegida o detectada, les criatures no s'hi poden comunicar telepàticament a menys que ell els ho permeti, i l'objectiu té avantatge en les tirades de salvació contra qualsevol efecte que determinaria si està dient la veritat."
			],
			"areaTags": [
				"ST"
			]
		}
	]
}
